zirkus/__init__.py
zirkus-0.0.1.dist-info/LICENSE.txt
zirkus-0.0.1.dist-info/METADATA
zirkus-0.0.1.dist-info/RECORD
zirkus-0.0.1.dist-info/WHEEL
zirkus-0.0.1.dist-info/top_level.txt
